lkops/.git/COMMIT_EDITMSG
lkops/.git/FETCH_HEAD
lkops/.git/HEAD
lkops/.git/config
lkops/.git/description
lkops/.git/hooks/applypatch-msg.sample
lkops/.git/hooks/commit-msg.sample
lkops/.git/hooks/fsmonitor-watchman.sample
lkops/.git/hooks/post-update.sample
lkops/.git/hooks/pre-applypatch.sample
lkops/.git/hooks/pre-commit.sample
lkops/.git/hooks/pre-merge-commit.sample
lkops/.git/hooks/pre-push.sample
lkops/.git/hooks/pre-rebase.sample
lkops/.git/hooks/pre-receive.sample
lkops/.git/hooks/prepare-commit-msg.sample
lkops/.git/hooks/update.sample
lkops/.git/index
lkops/.git/info/exclude
lkops/.git/logs/HEAD
lkops/.git/logs/refs/heads/main
lkops/.git/logs/refs/remotes/origin/HEAD
lkops/.git/logs/refs/remotes/origin/main
lkops/.git/objects/01/83a927663e9bdc0a441b3fdbad0cc38daf2ee0
lkops/.git/objects/02/df14a0f0f224da3972349aa482605b6bbad026
lkops/.git/objects/07/39c80b034f7e2d09c413d33614657d69e4a0db
lkops/.git/objects/09/05b80a92d692dec2e231ad621ffad1974f9812
lkops/.git/objects/0a/70b116685b6fa3bf74c91bd8517b00fb05eef7
lkops/.git/objects/0a/c009c1ea997da4c01cf0e8c790981875a78600
lkops/.git/objects/0c/bf2b9351fd2fc5995b8f72c5d4fadf7a2f9505
lkops/.git/objects/0d/3cce474d13d65d16f687419abe7afeab507640
lkops/.git/objects/0e/0eb306ef258c3fae89ef4c68cf6d1dd938c218
lkops/.git/objects/12/e27dce219ce6db61c4ff583fb9e6532bda91d0
lkops/.git/objects/13/7fda3583d381e7d6c930f7aeefc116c8c5cd59
lkops/.git/objects/16/6ec3729a262ae2d08919d2b464ac0b2e8af499
lkops/.git/objects/16/ce39dbb4d67c4c702e1b340f8d5d03272f7fda
lkops/.git/objects/17/a0ca6c0994a3799b28dddadd7cb68190430e62
lkops/.git/objects/1d/b0738646c4b3e79eefea2c1aa750a6902d4dc5
lkops/.git/objects/1e/916aa83a809512f881410cc323664f91c76541
lkops/.git/objects/1f/a360dd05c82176c788662d0dbe462ac983cced
lkops/.git/objects/1f/cbbf8d657f1bf2d392266333744225d5276c8a
lkops/.git/objects/20/70ee9118c9c0e69e23b519ebac9d1bbca6b141
lkops/.git/objects/26/d1a4d2855c1e6743f960b84cfb4c5eacdc00b7
lkops-0.1.0.dist-info/WHEEL
lkops-0.1.0.dist-info/METADATA
lkops-0.1.0.dist-info/RECORD
