Metadata-Version: 2.1
Name: lkops
Version: 0.1.0
Summary: Easy ops.
Author: songhaoyanga
Author-email: 1627635056@qq.com
Requires-Python: >=3.8,<4.0
Classifier: Programming Language :: Python :: 3
Classifier: Programming Language :: Python :: 3.8
Classifier: Programming Language :: Python :: 3.9
Classifier: Programming Language :: Python :: 3.10
Classifier: Programming Language :: Python :: 3.11
Requires-Dist: loguru (>=0.6.0,<0.7.0)
Requires-Dist: numpy (>=1.24.1,<2.0.0)
